{
  "saves": 11634,
  "playlist_name": "so you like the dress by dijon?",
  "last_updated": "today at 10:58pm EDT",
  "history": [
    {
      "date": "2026-06-21",
      "saves": 11548
    },
    {
      "date": "2026-06-22",
      "saves": 11561
    },
    {
      "date": "2026-06-23",
      "saves": 11575
    },
    {
      "date": "2026-06-24",
      "saves": 11588
    },
    {
      "date": "2026-06-25",
      "saves": 11608
    },
    {
      "date": "2026-06-26",
      "saves": 11625
    },
    {
      "date": "2026-06-27",
      "saves": 11634
    }
  ]
}